{
  "type": "item",
  "version": "15.12.1",
  "data": {
    "3004": {
      "name": "Manamune",
      "description": "<mainText><stats><attention>35</attention> Attack Damage<br><attention>500</attention> Mana<br><attention>15</attention> Ability Haste</stats><br><br><passive>Awe</passive><br>Gain <scaleAD> bonus Attack Damage</scaleAD>.<br><br><passive>Manaflow</passive> (8s, max 4 charges)<br>Landing Attacks and Abilities grants <scaleMana>3 max Mana</scaleMana> (doubled vs. champions).<br>Transforms into <rarityLegendary>Muramana</rarityLegendary> at <scaleMana>360 max Mana</scaleMana>.</mainText>",
      "colloq": "",
      "plaintext": "Increases Attack Damage based on maximum Mana",
      "from": [
        "3070",
        "3133",
        "1036"
      ],
      "image": {
        "full": "3004.png",
        "sprite": "item2.png",
        "group": "item",
        "x": 0,
        "y": 288,
        "w": 48,
        "h": 48
      },
      "gold": {
        "base": 1100,
        "purchasable": true,
        "total": 2900,
        "sell": 2030
      },
      "tags": [
        "Damage",
        "Mana",
        "CooldownReduction",
        "OnHit",
        "AbilityHaste"
      ],
      "maps": {
        "11": true,
        "12": true,
        "21": true,
        "22": false,
        "30": false,
        "33": false,
        "35": true
      },
      "stats": {
        "FlatMPPoolMod": 500,
        "FlatPhysicalDamageMod": 35
      },
      "depth": 3
    }
  }
}